nilan_proxy/__init__.py
nilan_proxy/const.py
nilan_proxy/nilan_proxy.py
nilan_proxy/nilan_proxy_modeladapter.py
nilan_proxy/models/__init__.py
nilan_proxy/models/basemodel.py
nilan_proxy/models/cts400.py
nilan_proxy/models/cts602.py
nilan_proxy/models/cts602light.py
nilan_proxy/models/optima250.py
nilan_proxy/models/optima251.py
nilan_proxy/models/optima260.py
nilan_proxy/models/optima270.py
nilan_proxy/models/optima301.py
nilan_proxy/models/optima312.py
nilan_proxy/models/optima314.py
nilan_proxy/protocol/__init__.py
nilan_proxy/protocol/command_builder.py
nilan_proxy/protocol/packet.py
nilan_proxy/protocol/payload.py
nilan_proxy/protocol/payload_cp_id.py
nilan_proxy/protocol/payload_crypt.py
nilan_proxy/protocol/payload_ipx.py
nilan_proxy-1.0.2.dist-info/LICENSE
nilan_proxy-1.0.2.dist-info/METADATA
nilan_proxy-1.0.2.dist-info/WHEEL
nilan_proxy-1.0.2.dist-info/top_level.txt
nilan_proxy-1.0.2.dist-info/RECORD
