Metadata-Version: 2.1
Name: nilan_proxy
Version: 1.0.2
Summary: A library to interface with Nilan Gateway and Genvex Connect enabled ventilation units.
Home-page: https://github.com/HairingX/nilan_proxy
Author: HairingX
License: GPLv3
Keywords: Nilan,Nilan Proxy,CTS 602,CTS 400,Genvex,Genvex Connect,Nabto,Optima 270,Optima 260,Optima 251,Optima 250,library,Home Automation
Classifier: Development Status :: 3 - Alpha
Classifier: Programming Language :: Python :: 3.12
Classifier: Intended Audience :: Developers
Classifier: Topic :: Software Development :: Libraries
Classifier: License :: OSI Approved :: GNU General Public License v3 (GPLv3)
Requires-Python: >=3.12
License-File: LICENSE
